sshkube/__init__.py
sshkube/__main__.py
sshkube/socat.py
sshkube-0.2.3.dist-info/LICENSE
sshkube-0.2.3.dist-info/METADATA
sshkube-0.2.3.dist-info/WHEEL
sshkube-0.2.3.dist-info/entry_points.txt
sshkube-0.2.3.dist-info/RECORD
