Metadata-Version: 2.3
Name: sshkube
Version: 0.2.3
Summary: Access kubernetes clusters over ssh
Author: Daniel J. B. Clarke
Author-email: u8sand@gmail.com
Requires-Python: >=3.10
Classifier: Programming Language :: Python :: 3
Classifier: Programming Language :: Python :: 3.10
Classifier: Programming Language :: Python :: 3.11
Classifier: Programming Language :: Python :: 3.12
Classifier: Programming Language :: Python :: 3.13
Requires-Dist: click (>=8.2.1,<9.0.0)
Requires-Dist: python-dotenv (>=1.1.1,<2.0.0)
Requires-Dist: pyyaml (>=6.0.2,<7.0.0)
Requires-Dist: winloop (>=0.1.8,<0.2.0) ; sys_platform == "win32"
